{
  "toolKey": "decToBin",
  "locale": "ro",
  "metadata": {
    "title": "DEC în BIN – convertor",
    "description": "Convertiți numere zecimale în binare și invers.",
    "ogImage": "/assets/tools/jpg-png-to-webp-converter/jpg-png-to-webp-unlimited-en.webp",
    "path": "/ro/instrumente/convertor-zecimal-in-binar"
  },
  "hero": {
    "title": "DEC în BIN",
    "description": "Acest convertor calculează instantaneu. Introduceți o valoare și rezultatul apare imediat.",
    "backgroundImage": "/assets/tools/jpg-png-to-webp-converter/jpg-png-to-webp-unlimited-en.webp"
  },
  "breadcrumbs": {
    "second": {
      "href": "/ro/instrumente",
      "label": "Instrumente"
    },
    "third": {
      "href": "/ro/instrumente/convertor-zecimal-in-binar",
      "label": "DEC în BIN"
    }
  },
  "schemas": {
    "software": {
      "name": "DEC în BIN – convertor",
      "alternateName": ["DEC în BIN"],
      "applicationCategory": "UtilitiesApplication",
      "applicationSubCategory": "UnitConverter",
      "description": "Convertiți numere zecimale în binare și invers.",
      "featureList": ["Conversie bidirecțională în timp real", "Toate convertoarele într-un singur loc", "Copierea rezultatului în clipboard", "Calcul local în browser"]
    },
    "howTo": {
      "name": "Cum să utilizați convertorul",
      "description": "Ghid rapid pentru utilizarea convertorului.",
      "totalTime": "PT1M",
      "steps": [
        {
          "name": "Introduceți valoarea",
          "text": "Scrieți un număr în câmpul de introducere din stânga."
        },
        {
          "name": "Citiți rezultatul",
          "text": "Rezultatul conversiei apare instantaneu în câmpul adiacent."
        },
        {
          "name": "Copiați sau inversați",
          "text": "Faceți clic pe Copiați rezultatul sau pe Inversați pentru a converti în direcția opusă."
        }
      ]
    }
  },
  "contentBlocks": [
    {
      "type": "gap",
      "variant": "line"
    },
    {
      "type": "sectionBasic",
      "title": "Când trebuie să folosiți: DEC în BIN?",
      "html": "<p class=\"text-mid mb-4\">Binary (base-2) is the fundamental number system of computers. Every piece of data — text, images, programs — is stored as sequences of 0s and 1s. Understanding binary is essential for programming, networking, and computer science.</p><p class=\"text-mid mb-4\">Each binary digit (bit) represents a power of 2: ...128, 64, 32, 16, 8, 4, 2, 1. For example: decimal 42 = binary 101010 (32+8+2).</p><p class=\"text-mid mb-4\">Common uses: IP addresses, subnet masks, bitwise operations, permissions (chmod), and understanding how computers store numbers.</p><p class=\"text-mid\">All calculations run locally in your browser — nothing is sent to any server.</p>",
      "imageSrc": "/assets/tools/jpg-png-to-webp-converter/jpg-png-to-webp-unlimited-en.webp",
      "imageAlt": "DEC în BIN – Arteon"
    },
    {
      "type": "gap",
      "size": "xs"
    },
    {
      "type": "sectionSteps",
      "title": "Cum să utilizați convertorul?",
      "grid": "three",
      "items": [
        {
          "title": "1. Introduceți valoarea",
          "description": "Scrieți un număr în câmpul de introducere. Puteți folosi punctul sau virgula ca separator zecimal.",
          "icon": "RiInputMethodLine"
        },
        {
          "title": "2. Citiți rezultatul",
          "description": "Rezultatul conversiei apare instantaneu în câmpul adiacent – fără a da clic.",
          "icon": "RiLoopLeftLine"
        },
        {
          "title": "3. Copiați sau inversați",
          "description": "Faceți clic pe Copiați rezultatul sau folosiți butonul Inversați.",
          "icon": "RiClipboardLine"
        }
      ]
    },
    {
      "type": "gap",
      "variant": "line"
    },
    {
      "type": "sectionSteps",
      "title": "Când este util acest convertor?",
      "grid": "two",
      "items": [
        {
          "icon": "RiCodeSSlashLine",
          "title": "Dezvoltare web",
          "description": "Operații pe biți, măști, flag-uri: 0xFF = 11111111."
        },
        {
          "icon": "RiWifiLine",
          "title": "Internet",
          "description": "Măști de subrețea: 255.255.255.0 = /24 (24 de unu în binar)."
        },
        {
          "icon": "RiShieldKeyholeLine",
          "title": "Permisiuni Unix",
          "description": "chmod 755 = 111 101 101 în binar."
        },
        {
          "icon": "RiCpuLine",
          "title": "Electronică",
          "description": "Registre, porturi I/O, protocoale de comunicație."
        }
      ]
    },
    {
      "type": "gap",
      "variant": "line"
    },
    {
      "type": "sectionSteps",
      "title": "Ce face acest convertor special?",
      "grid": "two",
      "items": [
        {
          "icon": "RiShieldCheckLine",
          "title": "Confidențialitate completă",
          "description": "Toate calculele se fac local, în browserul dvs. Nicio dată nu este trimisă la vreun server."
        },
        {
          "icon": "RiTimeLine",
          "title": "Rezultate în timp real",
          "description": "Rezultatul se actualizează instant pe măsură ce tastați – fără a apăsa vreun buton."
        },
        {
          "icon": "RiArrowLeftRightLine",
          "title": "Conversie bidirecțională",
          "description": "Butonul Inversare vă permite să convertiți în ambele direcții cu un singur clic."
        },
        {
          "icon": "RiTableLine",
          "title": "Tabel de referință",
          "description": "Un tabel gata cu valori convertite frecvent și descrieri contextuale."
        }
      ]
    },
    {
      "type": "gap",
      "variant": "line"
    },
    {
      "type": "sectionInfo",
      "title": "Cum funcționează conversia?",
      "html": "<p class=\"text-mid mb-4\">Împărțiți repetat la 2 și notați resturile. Citiți de jos în sus.</p><p class=\"text-mid\">8 biți = 1 octet = valori 0–255.</p>"
    },
    {
      "type": "gap",
      "variant": "line"
    },
    {
      "type": "sectionInfo",
      "title": "Sfaturi practice",
      "html": "<ul class=\"list-disc pl-5 space-y-2 text-mid\"><li>Puterile lui 2: 1, 2, 4, 8, 16, 32, 64, 128, 256, 512, 1024.</li><li>1 octet = 8 biți = 0–255. Frecvent în culori RGB, coduri ASCII.</li><li>Adresă IP: 192.168.1.1 = 11000000.10101000.00000001.00000001.</li><li>Numerele negative folosesc complement față de doi în majoritatea sistemelor.</li></ul>"
    },
    {
      "type": "gap",
      "variant": "line"
    },
    {
      "type": "sectionFeatureComparison",
      "title": "Decimal vs Binary",
      "featureLabel": "Proprietate",
      "plans": [
        {
          "id": "unit1",
          "name": "Decimal (base-10)"
        },
        {
          "id": "unit2",
          "name": "Binary (base-2)",
          "highlighted": true
        }
      ],
      "features": [
        {
          "name": "Cifre",
          "values": {
            "unit1": "0–9",
            "unit2": "0–1"
          }
        },
        {
          "name": "Utilizat de",
          "values": {
            "unit1": "Oameni",
            "unit2": "Calculatoare"
          }
        },
        {
          "name": "Exemplu: 42",
          "values": {
            "unit1": "42",
            "unit2": "101010"
          }
        },
        {
          "name": "Exemplu: 255",
          "values": {
            "unit1": "255",
            "unit2": "11111111"
          }
        },
        {
          "name": "Lizibilitate",
          "values": {
            "unit1": "Ușor pentru oameni",
            "unit2": "Lung dar nativ pentru calculatoare"
          }
        }
      ]
    },
    {
      "type": "gap",
      "variant": "line"
    },
    {
      "type": "faq",
      "title": "Întrebări frecvente",
      "openByDefault": 1,
      "items": [
        {
          "question": "Ce este 10 in Binär?",
          "answer": "Zecimal 10 = Binar 1010 (8+2)."
        },
        {
          "question": "Ce este 255 in Binär?",
          "answer": "255 = 11111111 (opt de unu). Maximul unui octet."
        },
        {
          "question": "Calculele se fac local?",
          "answer": "Da. Toate calculele se efectuează în browserul dumneavoastră."
        }
      ]
    },
    {
      "type": "gap",
      "variant": "line"
    },
    {
      "type": "contactForm",
      "title": "Ajutați-ne să ne îmbunătățim instrumentele",
      "description": "Aveți o idee, ați găsit o eroare sau doriți să sugerați o funcție? Scrieți-ne – răspundem în 24 de ore.",
      "imageSrc": "/assets/tools/jpg-png-to-webp-converter/jpg-png-to-webp-unlimited-en.webp",
      "imageAlt": "DEC în BIN – Arteon",
      "defaultSubject": "Feedback: dec-to-bin"
    },
    {
      "type": "gap",
      "variant": "line"
    },
    {
      "type": "toolsCarousel",
      "title": "Alte instrumente gratuite"
    },
    {
      "type": "gap",
      "size": "sm"
    }
  ]
}
