{
  "toolKey": "csvToJson",
  "locale": "hu",
  "metadata": {
    "title": "CSV JSON konverter — CSV JSON",
    "description": "CSV konvertálása JSON formátumba. Automatikus elemzés és formázás. Ingyenes.",
    "ogImage": "/assets/tools/jpg-png-to-webp-converter/jpg-png-webp-konverter-hu.webp",
    "path": "/hu/eszkozok/csv-json-konverter"
  },
  "hero": {
    "title": "CSV JSON konverter",
    "description": "CSV konvertálása JSON formátumba. Automatikus elemzés és formázás. Ingyenes.",
    "backgroundImage": "/assets/tools/jpg-png-to-webp-converter/jpg-png-webp-konverter-hu.webp"
  },
  "breadcrumbs": {
    "second": {
      "href": "/hu/eszkozok",
      "label": "Eszközök"
    },
    "third": {
      "href": "/hu/eszkozok/csv-json-konverter",
      "label": "CSV JSON konverter"
    }
  },
  "schemas": {
    "software": {
      "name": "CSV JSON konverter",
      "applicationCategory": "MultimediaApplication",
      "applicationSubCategory": "DataConverter",
      "description": "CSV konvertálása JSON formátumba. Automatikus elemzés és formázás. Ingyenes.",
      "featureList": ["CSV to JSON conversion", "Batch conversion", "Local browser processing"],
      "alternateName": ["Convert CSV to JSON", "CSV to JSON", "Free CSV to JSON converter"]
    },
    "howTo": {
      "name": "Hogyan konvertáljuk CSV-t JSON-vé",
      "description": "CSV konvertálása JSON formátumba. Automatikus elemzés és formázás. Ingyenes.",
      "steps": [
        {
          "position": 1,
          "name": "Illessze be az adatokat",
          "text": "Illessze be a CSV adatokat a beviteli mezőbe."
        },
        {
          "position": 2,
          "name": "Konvertálás",
          "text": "Kattintson a Konvertálás gombra a CSV adatok JSON formátumba alakításához."
        },
        {
          "position": 3,
          "name": "Másolás vagy letöltés",
          "text": "Másolja a JSON kimenetet, vagy töltse le fájlként."
        }
      ]
    }
  },
  "contentBlocks": [
    {
      "type": "gap",
      "variant": "line"
    },
    {
      "type": "sectionBasic",
      "title": "Miért érdemes CSV-t JSON-vé konvertálni?",
      "html": "<p class=\"text-mid mb-4\">A CSV szeles korben hasznalt fajlformatum nagy kompatibilitassal. A felhasznalasi esettol fuggoen a JSON formaba torteno konvertalas jelentos elonyoket kinaalhat — kisebb fajlok, jobb minoseg vagy szelessbb platformtamogatas.</p><p class=\"text-mid mb-4\">Ez az ingyenes online konvertalo kozvetlenul a bongeszoben alakitja at a CSV fajlokat JSON formatumba. Semmilyen fajl nem kerul feltoltesre — az egesz folyamat helyben tortenik az Onn eszkozeen.</p><p class=\"text-mid\">Konvertaljon annyi fajlt, amennyit szeretne, napi limit, regisztracio es vizjel nelkul. Huzza be a fajlokat, allitsa be a minoseg, es toltse le az eredmenyeket.</p>",
      "imageSrc": "/assets/tools/jpg-png-to-webp-converter/jpg-png-webp-konverter-hu.webp",
      "imageAlt": "CSV to JSON conversion",
      "variant": "right"
    },
    {
      "type": "gap",
      "size": "xs"
    },
    {
      "type": "sectionSteps",
      "title": "Hogyan konvertáljuk CSV-t JSON-vé",
      "grid": "three",
      "items": [
        {
          "title": "Illessze be az adatokat",
          "description": "Illessze be a CSV adatokat a beviteli mezőbe.",
          "icon": "RiUploadCloud2Line"
        },
        {
          "title": "Konvertálás",
          "description": "Kattintson a Konvertálás gombra a CSV adatok JSON formátumba alakításához.",
          "icon": "RiSettings3Line"
        },
        {
          "title": "Másolás vagy letöltés",
          "description": "Másolja a JSON kimenetet, vagy töltse le fájlként.",
          "icon": "RiDownloadLine"
        }
      ]
    },
    {
      "type": "gap",
      "variant": "line"
    },
    {
      "type": "sectionSteps",
      "title": "Mi teszi különlegessé ezt a konvertert?",
      "grid": "two",
      "items": [
        {
          "icon": "RiShieldCheckLine",
          "title": "Teljes adatvédelem",
          "description": "A fájlok teljes mértékben a böngészőben kerülnek feldolgozásra. Semmi nem kerül szerverre."
        },
        {
          "icon": "RiInfinityLine",
          "title": "Nincs korlát",
          "description": "Konvertáljon annyi fájlt, amennyit csak akar. Nincs napi limit, nincs méretkorlátozás."
        },
        {
          "icon": "RiImageEditLine",
          "title": "Minőségszabályozás",
          "description": "Állítsa be a beállításokat a tökéletes egyensúly megtalálásához a fájlméret és a minőség között."
        },
        {
          "icon": "RiFlashlightLine",
          "title": "Azonnali konverzió",
          "description": "Minden feldolgozás helyben történik modern böngésző API-k segítségével."
        }
      ]
    },
    {
      "type": "gap",
      "variant": "line"
    },
    {
      "type": "sectionFeatureComparison",
      "title": "CSV vs JSON – formátum-összehasonlítás",
      "plans": [
        {
          "id": "csv",
          "name": "CSV"
        },
        {
          "id": "json",
          "name": "JSON",
          "highlighted": true
        }
      ],
      "features": [
        {
          "name": "Beágyazott adatok",
          "values": {
            "csv": false,
            "json": true
          }
        },
        {
          "name": "Táblázatos adatok",
          "values": {
            "csv": true,
            "json": false
          }
        },
        {
          "name": "Sémavalidáció",
          "values": {
            "csv": false,
            "json": true
          }
        },
        {
          "name": "Ember által olvasható",
          "values": {
            "csv": true,
            "json": true
          }
        },
        {
          "name": "API-szabvány",
          "values": {
            "csv": false,
            "json": true
          }
        },
        {
          "name": "Kompakt szintaxis",
          "values": {
            "csv": true,
            "json": true
          }
        }
      ]
    },
    {
      "type": "gap",
      "variant": "line"
    },
    {
      "type": "sectionInfo",
      "title": "Mennyit takarit meg CSV JSON konvertalasaval?",
      "html": "<p class=\"text-mid mb-4\">A megtakaritas a forras tipusatol es tomoritesitol fugg:</p><div class=\"mt-6 grid gap-4 md:grid-cols-3\"><div class=\"rounded-lg border border-neutral-200 bg-white p-4\"><p class=\"text-dark mb-2 font-semibold\">Fenykep</p><p class=\"text-light text-sm\">2.4 MB → 890 KB</p><p class=\"text-success-icon mt-1 text-sm font-medium\">Megtakaritas: ~63%</p></div><div class=\"rounded-lg border border-neutral-200 bg-white p-4\"><p class=\"text-dark mb-2 font-semibold\">Termekkep</p><p class=\"text-light text-sm\">500 KB → 185 KB</p><p class=\"text-success-icon mt-1 text-sm font-medium\">Megtakaritas: ~63%</p></div><div class=\"rounded-lg border border-neutral-200 bg-white p-4\"><p class=\"text-dark mb-2 font-semibold\">Kepernykep / banner</p><p class=\"text-light text-sm\">350 KB → 230 KB</p><p class=\"text-success-icon mt-1 text-sm font-medium\">Megtakaritas: ~34%</p></div></div><p class=\"text-light mt-4 text-sm\">A tenyleges megtakaritas valtozhat tartalom es beallitasok szerint.</p>"
    },
    {
      "type": "gap",
      "variant": "line"
    },
    {
      "type": "sectionSteps",
      "title": "Tippek CSV JSON konvertalasahoz",
      "description": "Tippek a gyakori problemaak elkerulesere:",
      "grid": "two",
      "items": [
        {
          "icon": "RiFileImageLine",
          "title": "Nagyon nagy fajlok",
          "description": "4000×4000 px feletti kepek lassabbak lehetnek. Ossza 10–20 darabos kotetekre."
        },
        {
          "icon": "RiFlashlightLine",
          "title": "Mar tomoriteett fajlok",
          "description": "Ha a CSV mar erosen tomoriteett volt, JSON konvertalas keveset takarithat."
        },
        {
          "icon": "RiPaletteLine",
          "title": "Atlatszosag",
          "description": "JSON nem tamogatja az atlatszosagot. Feher hatter lesz. Hasznaljon PNG-t vagy WebP-t."
        },
        {
          "icon": "RiStackLine",
          "title": "Orizze meg az eredetiket",
          "description": "A veszteseges konvertalas visszafordithatatlan. Orizze meg a CSV fajlok masolatait."
        }
      ]
    },
    {
      "type": "gap",
      "variant": "line"
    },
    {
      "type": "faq",
      "title": "Gyakran ismételt kérdések a CSV-JSON konverzióról",
      "openByDefault": 0,
      "items": [
        {
          "question": "Ingyenes a CSV konvertálása JSON-vé?",
          "answer": "Igen, ez a konverter teljesen ingyenes és korlátlan. Nincs regisztráció, nincs vízjel."
        },
        {
          "question": "Feltölti a fájljaimat a konverter?",
          "answer": "Nem. Minden feldolgozás helyben történik a böngészőben. A fájlok soha nem hagyják el az eszközét."
        },
        {
          "question": "Konvertálhatok egyszerre több fájlt?",
          "answer": "Igen, a konverter támogatja a kötegelt konverziót."
        },
        {
          "question": "Működik a konverter mobilon?",
          "answer": "Igen, minden modern böngészővel rendelkező eszközön működik."
        },
        {
          "question": "Biztonsagos CSV JSON konvertalasa?",
          "answer": "Igen. Minden helyben tortenik a bongeszoben Canvas API-val. Semmi nem kerul szerverre."
        },
        {
          "question": "Konvertalhatok tobb CSV fajlt egyszerre?",
          "answer": "Igen. Kotegelt konvertalas limit nelkul. Huzza a fajlokat a konvertalora."
        },
        {
          "question": "Minden bongeszo tamogatja a JSON-t?",
          "answer": "JSON-t a Chrome, Firefox, Safari, Edge es Opera tamogatja."
        }
      ]
    },
    {
      "type": "gap",
      "variant": "line"
    },
    {
      "type": "contactForm",
      "title": "Segítsen javítani eszközeinket",
      "description": "Van ötlete, hibát talált vagy javaslatot szeretne tenni? Írjon nekünk – 24 órán belül válaszolunk.",
      "imageSrc": "/assets/tools/jpg-png-to-webp-converter/jpg-png-webp-konverter-hu.webp",
      "imageAlt": "Contact",
      "defaultSubject": "CSV JSON konverter"
    },
    {
      "type": "gap",
      "variant": "line"
    },
    {
      "type": "toolsCarousel",
      "title": "Más eszközök"
    },
    {
      "type": "gap",
      "size": "sm"
    }
  ]
}
