{
  "nav": {
    "mainNavigation": "Huvudnavigering",
    "logoAlt": "Arteon - företagslogotyp",
    "closeMenu": "Stäng menyn",
    "openMenu": "Öppna menyn",
    "closeToolsList": "Stäng verktygslistan",
    "openToolsList": "Öppna verktygslistan",
    "toolsLabel": "Verktyg",
    "mobileMenu": "Mobilmeny",
    "aboutLabel": "Om oss",
    "contactLabel": "Kontakt"
  },
  "footer": {
    "copyright": "Alla rättigheter förbehållna.",
    "description": "Gratis verktyg för webbutvecklare, designers och marknadsförare.",
    "companyDataLabel": "Företagsuppgifter",
    "toolsLabel": "Verktyg",
    "legalLabel": "Juridiska dokument",
    "cookieSettingsLabel": "Cookie-inställningar"
  },
  "desktopOnly": {
    "title": "Detta verktyg fungerar på en större skärm",
    "description": "För att använda detta verktyg bekvämt, öppna det på en bärbar dator, stationär dator eller surfplatta i liggande läge.",
    "tipTitle": "Tips",
    "tipText": "Om du använder en surfplatta, byt till liggande läge — när fönsterbredden är tillräcklig laddas verktyget automatiskt."
  },
  "cookie": {
    "title": "Cookies och integritet",
    "description": "Vi använder cookies för webbplatsens funktion, trafikanalys och annonsvisning. Läs mer i",
    "setPreferences": "Ange inställningar",
    "privacyPolicy": "Integritetspolicy",
    "privacyPolicyHref": "/sv/integritetspolicy",
    "reject": "Avvisa alla",
    "settings": "Inställningar",
    "accept": "Acceptera alla",
    "panelTitle": "Integritetsinställningar",
    "panelDescription": "Samtyckesinställningar för databehandling.",
    "categoriesLegend": "Kategorier",
    "essentialTitle": "Nödvändiga",
    "essentialDescription": "Webbplatsen kan inte fungera utan dessa. Samlar inte in marknadsföringsdata.",
    "essentialStatus": "Alltid aktiv",
    "analyticsTitle": "Analys (GA4)",
    "analyticsDescription": "Besöksstatistik. Aktiverar Google Analytics 4 med ditt samtycke.",
    "analyticsLabel": "Aktivera GA4-analys",
    "adsTitle": "Annonser (Google AdSense)",
    "adsDescription": "Personanpassade annonser baserade på dina intressen.",
    "adsLabel": "Aktivera personanpassade annonser",
    "changeDecision": "Du kan ändra ditt beslut när som helst",
    "save": "Spara"
  },
  "skipToContent": "Hoppa till innehåll",
  "legal": [
    {
      "key": "privacy",
      "href": "/sv/integritetspolicy",
      "label": "Integritetspolicy"
    },
    {
      "key": "terms",
      "href": "/sv/anvandarvillkor",
      "label": "Anvandarvillkor"
    }
  ],
  "breadcrumbs": {
    "home": "Startsida",
    "ariaLabel": "navigering"
  },
  "contactForm": {
    "nameLabel": "För- och efternamn",
    "namePlaceholder": "Erik Johansson",
    "emailLabel": "E-post",
    "emailPlaceholder": "erik.johansson@gmail.com",
    "subjectLabel": "Ämne",
    "subjectPlaceholder": "t.ex. Felrapport | Verktygsförslag | Fråga",
    "messageLabel": "Meddelande",
    "messagePlaceholder": "Beskriv din fråga eller ditt förslag...",
    "send": "Skicka",
    "error": "Något gick fel. Kontrollera dina uppgifter och försök igen.",
    "success": "Meddelande skickat! Vi svarar så snart som möjligt."
  },
  "toolsCarousel": {
    "defaultTitle": "Gratis verktyg",
    "seeAllTools": "Visa alla verktyg",
    "carouselLabel": "Verktygskarusell",
    "scrollLeft": "Scrolla vänster",
    "scrollRight": "Scrolla höger",
    "carouselNavigation": "Karusellnavigering",
    "goToSlide": "Gå till bild",
    "of": "av",
    "slide": "Bild",
    "tool": "Verktyg",
    "openTool": "Öppna verktyg"
  },
  "languageSwitcher": {
    "switchTitle": "Byt till svenska",
    "toggleLabel": "Ändra språk",
    "chooseLabel": "Välj språk",
    "popularLabel": "Populära",
    "otherLabel": "Övriga",
    "closeModalLabel": "Stäng"
  },
  "mobileNav": {
    "close": "Stäng",
    "services": "Tjänster",
    "contact": "Kontakt"
  },
  "infoBanner": {
    "text": "E-postsignatur-generatorn är uppdaterad – upptäck nya funktioner",
    "linkText": "verktyg"
  }
}
