{
  "nav": {
    "mainNavigation": "Navigasi utama",
    "logoAlt": "Arteon - logo perusahaan",
    "closeMenu": "Tutup menu",
    "openMenu": "Buka menu",
    "closeToolsList": "Tutup daftar alat",
    "openToolsList": "Buka daftar alat",
    "toolsLabel": "Alat",
    "mobileMenu": "Menu mobile",
    "aboutLabel": "Tentang kami",
    "contactLabel": "Kontak"
  },
  "footer": {
    "copyright": "Hak cipta dilindungi.",
    "description": "Alat gratis untuk pengembang web, desainer, dan pemasar.",
    "companyDataLabel": "Data perusahaan",
    "toolsLabel": "Alat",
    "legalLabel": "Dokumen hukum",
    "cookieSettingsLabel": "Pengaturan cookie"
  },
  "desktopOnly": {
    "title": "Alat ini berfungsi di layar yang lebih besar",
    "description": "Untuk menggunakan alat ini dengan nyaman, buka di laptop, komputer desktop, atau tablet dalam mode lanskap.",
    "tipTitle": "Tips",
    "tipText": "Jika menggunakan tablet, alihkan ke mode lanskap - saat lebar jendela cukup besar, alat akan dimuat secara otomatis."
  },
  "cookie": {
    "title": "Cookie dan privasi",
    "description": "Kami menggunakan cookie untuk fungsi situs, analisis lalu lintas, dan menampilkan iklan. Pelajari lebih lanjut di",
    "setPreferences": "Atur preferensi",
    "privacyPolicy": "Kebijakan privasi",
    "privacyPolicyHref": "/id/kebijakan-privasi",
    "reject": "Tolak semua",
    "settings": "Pengaturan",
    "accept": "Terima semua",
    "panelTitle": "Preferensi privasi",
    "panelDescription": "Pengaturan persetujuan untuk pemrosesan data.",
    "categoriesLegend": "Kategori",
    "essentialTitle": "Esensial",
    "essentialDescription": "Situs tidak dapat berfungsi tanpa ini. Tidak mengumpulkan data pemasaran.",
    "essentialStatus": "Selalu aktif",
    "analyticsTitle": "Analitik (GA4)",
    "analyticsDescription": "Statistik kunjungan. Mengaktifkan Google Analytics 4 dengan persetujuan Anda.",
    "analyticsLabel": "Aktifkan analitik GA4",
    "adsTitle": "Iklan (Google AdSense)",
    "adsDescription": "Iklan yang dipersonalisasi berdasarkan minat Anda.",
    "adsLabel": "Aktifkan iklan yang dipersonalisasi",
    "changeDecision": "Anda dapat mengubah keputusan kapan saja",
    "save": "Simpan"
  },
  "skipToContent": "Langsung ke konten",
  "legal": [
    {
      "key": "privacy",
      "href": "/id/kebijakan-privasi",
      "label": "Kebijakan privasi"
    }
  ],
  "breadcrumbs": {
    "home": "Beranda",
    "ariaLabel": "navigasi"
  },
  "contactForm": {
    "nameLabel": "Nama lengkap",
    "namePlaceholder": "Budi Santoso",
    "emailLabel": "Email",
    "emailPlaceholder": "budi.santoso@gmail.com",
    "subjectLabel": "Subjek",
    "subjectPlaceholder": "mis. Laporan bug | Saran alat | Pertanyaan",
    "messageLabel": "Pesan",
    "messagePlaceholder": "Jelaskan pertanyaan atau saran Anda...",
    "send": "Kirim",
    "error": "Terjadi kesalahan. Periksa data Anda dan coba lagi.",
    "success": "Pesan terkirim! Kami akan merespons secepat mungkin."
  },
  "toolsCarousel": {
    "defaultTitle": "Alat gratis",
    "seeAllTools": "Lihat semua alat",
    "carouselLabel": "Carousel alat",
    "scrollLeft": "Gulir ke kiri",
    "scrollRight": "Gulir ke kanan",
    "carouselNavigation": "Navigasi carousel",
    "goToSlide": "Ke slide",
    "of": "dari",
    "slide": "Slide",
    "tool": "Alat",
    "openTool": "Buka alat"
  },
  "languageSwitcher": {
    "switchTitle": "Beralih ke Bahasa Indonesia",
    "toggleLabel": "Ubah bahasa",
    "chooseLabel": "Pilih bahasa",
    "popularLabel": "Populer",
    "otherLabel": "Lainnya",
    "closeModalLabel": "Tutup"
  },
  "mobileNav": {
    "close": "Tutup",
    "services": "Layanan",
    "contact": "Kontak"
  },
  "infoBanner": {
    "text": "Pembaruan generator tanda tangan email - temukan fitur baru",
    "linkText": "alat"
  }
}
