{
  "sampleTextLabel": "Maandishi ya mfano",
  "exampleText": "Maandishi ya mfano ya tofauti ya WCAG 2.1",
  "exampleTextPlaceholder": "Ingiza kichwa, maandishi ya kitufe, au maudhui ya aya",
  "textColorLabel": "Rangi ya maandishi (foreground)",
  "selectTextColor": "Chagua rangi ya maandishi",
  "textColorPlaceholder": "#000000 au rgba(0,0,0,0.8)",
  "supportedFormats": "Miundo inayokubalika:",
  "backgroundColorLabel": "Rangi ya mandharinyuma (background)",
  "selectBackgroundColor": "Chagua rangi ya mandharinyuma",
  "backgroundColorPlaceholder": "#ffffff au hsl(0, 0%, 100%)",
  "swapColors": "Badilisha rangi",
  "resetColors": "Rejesha nyeusi juu ya nyeupe",
  "matchTargetLabel": "Lengo la kulinganisha",
  "matchColor": "Linganisha",
  "suggestedColor": "Rangi iliyopendekezwa",
  "applySuggestedColor": "Weka",
  "copy": "Nakili",
  "copied": "Imenakiliwa",
  "matchError": "Haijawezekana kupata lahaja inayokidhi kizingiti kilichochaguliwa.",
  "contrastRatio": "Uwiano wa tofauti",
  "colorReadError": "Imeshindwa kusoma rangi. Tumia muundo",
  "or": "au",
  "normalText": "Maandishi ya kawaida",
  "largeText": "Maandishi makubwa / yaliyokozeshwa",
  "icon": "Ikoni",
  "exampleNormalText": "Maandishi ya mfano ya kawaida",
  "exampleLargeText": "Kichwa / kitufe cha mfano",
  "iconPreview": "Hakiki ya ikoni kwenye mandharinyuma",
  "resultsLabel": "Matokeo ya jaribio la tofauti na hakiki",
  "badges": {
    "normalAA": "AA (min. 4.5:1)",
    "normalAAA": "AAA (min. 7:1)",
    "largeAA": "AA (min. 3:1)",
    "largeAAA": "AAA (min. 4.5:1)",
    "iconAA": "AA (min. 3:1)"
  }
}
