{
  "toolKey": "jpgToPng",
  "locale": "sv",
  "metadata": {
    "title": "JPG till PNG-konverterare – JPG PNG",
    "description": "Konvertera JPG-bilder till förlustfritt PNG. Lokal konvertering i webbläsaren.",
    "ogImage": "/assets/tools/jpg-png-to-webp-converter/jpg-png-till-webp-konverterare-sv.webp",
    "path": "/sv/verktyg/jpg-till-png-konverterare"
  },
  "hero": {
    "title": "JPG till PNG-konverterare",
    "description": "Konvertera JPG-bilder till förlustfritt PNG. Lokal konvertering i webbläsaren.",
    "backgroundImage": "/assets/tools/jpg-png-to-webp-converter/jpg-png-till-webp-konverterare-sv.webp"
  },
  "breadcrumbs": {
    "second": {
      "href": "/sv/verktyg",
      "label": "Verktyg"
    },
    "third": {
      "href": "/sv/verktyg/jpg-till-png-konverterare",
      "label": "JPG till PNG-konverterare"
    }
  },
  "schemas": {
    "software": {
      "name": "JPG till PNG-konverterare",
      "alternateName": [],
      "applicationCategory": "MultimediaApplication",
      "applicationSubCategory": "ImageConverter",
      "description": "Konvertera JPG-bilder till förlustfritt PNG. Lokal konvertering i webbläsaren.",
      "featureList": ["JPG till PNG-konvertering", "Förlustfri PNG-utdata", "Batchkonvertering", "Lokal webbläsarbearbetning", "Ingen filuppladdning krävs"]
    },
    "howTo": {
      "name": "Hur man konverterar JPG till PNG",
      "description": "Konvertera JPG-filer till PNG-format direkt i din webbläsare.",
      "steps": [
        {
          "name": "Lägg till JPG-filer",
          "text": "Dra JPG-filer till uppladdningsytan eller klicka för att välja filer från din enhet."
        },
        {
          "name": "Konvertera till PNG",
          "text": "Klicka på konvertera. PNG är förlustfritt — ingen kvalitetsinställning behövs."
        },
        {
          "name": "Ladda ner PNG-filer",
          "text": "Ladda ner dina konverterade PNG-filer enskilt eller alla på en gång."
        }
      ]
    }
  },
  "contentBlocks": [
    {
      "type": "sectionBasic",
      "title": "Varför konvertera JPG till PNG?",
      "html": "<p class=\"text-mid mb-4\">JPEG (JPG) är ett förlustbringande bildformat. Det används i stor utsträckning för fotografier.</p><p class=\"text-mid mb-4\">Konvertering av JPG till PNG (Portable Network Graphics) ger mer flexibilitet.</p><p class=\"text-mid mb-4\">PNG stödjer alfa-transparens.</p><p class=\"text-mid\">Denna konverterare arbetar lokalt i din webbläsare – dina filer lämnar aldrig din enhet. Inga uppladdningar, inga servrar, ingen registrering. Helt gratis.</p>",
      "imageSrc": "/assets/tools/jpg-png-to-webp-converter/jpg-png-till-webp-konverterare-sv.webp",
      "imageAlt": "JPG to PNG conversion",
      "variant": "right"
    },
    {
      "type": "gap",
      "variant": "line"
    },
    {
      "type": "sectionSteps",
      "title": "Så konverterar du JPG till PNG",
      "grid": "three",
      "items": [
        {
          "icon": "RiUploadCloud2Line",
          "title": "Ladda upp din JPG-fil",
          "description": "Dra och släpp din JPG-bild på konverteringsområdet eller klicka för att bläddra på din enhet. Du kan lägga till flera filer samtidigt."
        },
        {
          "icon": "RiSettings3Line",
          "title": "Justera inställningar",
          "description": "Välj önskade kvalitets- och utdatainställningar. Konverteraren visar en förhandsgranskning för jämförelse av JPG-originalet med PNG-resultatet."
        },
        {
          "icon": "RiDownloadLine",
          "title": "Ladda ner din PNG-fil",
          "description": "Klicka på nedladdningsknappen för att spara din konverterade PNG-fil. För flera filer, använd batchnedladdning."
        }
      ]
    },
    {
      "type": "gap",
      "variant": "line"
    },
    {
      "type": "sectionInfo",
      "title": "JPG vs PNG – de viktigaste skillnaderna",
      "html": "<div class=\"overflow-x-auto\"><table class=\"w-full text-sm\"><thead><tr class=\"border-b\"><th class=\"py-2 text-left\">Egenskap</th><th class=\"py-2 text-center\">JPG</th><th class=\"py-2 text-center\">PNG</th></tr></thead><tbody><tr class=\"border-b\"><td class=\"py-2\">Komprimering</td><td class=\"py-2 text-center\">Förlustbringande</td><td class=\"py-2 text-center\">Förlustfri</td></tr><tr class=\"border-b\"><td class=\"py-2\">Transparens</td><td class=\"py-2 text-center\">Nej</td><td class=\"py-2 text-center\">Ja</td></tr><tr class=\"border-b\"><td class=\"py-2\">Animation</td><td class=\"py-2 text-center\">Nej</td><td class=\"py-2 text-center\">Nej</td></tr><tr><td class=\"py-2\">Webbläsarstöd</td><td class=\"py-2 text-center\">universal</td><td class=\"py-2 text-center\">universal</td></tr></tbody></table></div>"
    },
    {
      "type": "gap",
      "variant": "line"
    },
    {
      "type": "sectionSteps",
      "title": "När ska du konvertera JPG till PNG?",
      "grid": "two",
      "items": [
        {
          "icon": "RiGlobalLine",
          "title": "Webboptimering",
          "description": "JPG → PNG – WordPress, Shopify, Quickbutik."
        },
        {
          "icon": "RiMailLine",
          "title": "E-post och delning",
          "description": "PNG – Gmail, Outlook, Telia."
        },
        {
          "icon": "RiShoppingBag3Line",
          "title": "E-handel",
          "description": "Blocket.se, Tradera, CDON, Amazon.se."
        },
        {
          "icon": "RiPrinterLine",
          "title": "Dokument och arkivering",
          "description": "PNG – tryckerier."
        }
      ]
    },
    {
      "type": "gap",
      "variant": "line"
    },
    {
      "type": "sectionSteps",
      "title": "Vad gör denna JPG-till-PNG-konverterare annorlunda?",
      "grid": "two",
      "items": [
        {
          "icon": "RiShieldCheckLine",
          "title": "Fullständig integritet",
          "description": "Dina JPG-filer bearbetas uteslutande i din webbläsare. Inget laddas upp till någon server."
        },
        {
          "icon": "RiInfinityLine",
          "title": "Inga begränsningar",
          "description": "Konvertera så många JPG-filer till PNG som du behöver. Inga dagliga gränser, inga storleksbegränsningar, inga vattenmärken."
        },
        {
          "icon": "RiImageEditLine",
          "title": "Kvalitetskontroll",
          "description": "Justera komprimeringsinställningarna för den perfekta balansen mellan filstorlek och bildkvalitet."
        },
        {
          "icon": "RiFlashlightLine",
          "title": "Omedelbar konvertering",
          "description": "All bearbetning sker lokalt med moderna webbläsar-API:er – snabbt och fungerar även utan internetanslutning."
        }
      ]
    },
    {
      "type": "gap",
      "variant": "line"
    },
    {
      "type": "sectionInfo",
      "title": "JPG-till-PNG-konvertering i praktiken",
      "html": "<p class=\"text-mid mb-4\">I Sverige och Norden är integritet avgörande – lokal bildkonvertering skyddar känsliga data.</p><p class=\"text-mid\">Blocket.se, Tradera, CDON, Amazon.se – WordPress, Shopify, Quickbutik.</p>"
    },
    {
      "type": "gap",
      "variant": "line"
    },
    {
      "type": "faq",
      "title": "Vanliga frågor om konvertering av JPG till PNG",
      "openByDefault": 0,
      "items": [
        {
          "question": "Är det gratis att konvertera JPG till PNG?",
          "answer": "Ja, denna JPG-till-PNG-konverterare är helt gratis utan begränsningar. Ingen registrering, inga vattenmärken."
        },
        {
          "question": "Laddas mina filer upp till en server?",
          "answer": "Nej. All bearbetning sker lokalt i din webbläsare. Dina filer lämnar aldrig din enhet."
        },
        {
          "question": "Tappar jag kvalitet vid konvertering?",
          "answer": "PNG stödjer förlustfri komprimering som bevarar originalkvaliteten."
        },
        {
          "question": "Kan jag konvertera flera filer samtidigt?",
          "answer": "Ja, konverteraren stödjer batchkonvertering."
        },
        {
          "question": "Fungerar konverteraren på mobila enheter?",
          "answer": "Ja, den fungerar på alla enheter med en modern webbläsare."
        }
      ]
    },
    {
      "type": "gap",
      "variant": "line"
    },
    {
      "type": "contactForm",
      "title": "Hjälp oss förbättra våra verktyg",
      "description": "Har du en idé, hittat en bugg eller vill föreslå en funktion? Skicka ett meddelande — vi svarar inom 24 timmar.",
      "imageSrc": "/assets/tools/jpg-png-to-webp-converter/jpg-png-till-webp-konverterare-sv.webp",
      "imageAlt": "JPG till PNG-konverterare – Arteon",
      "defaultSubject": "Feedback: JPG till PNG-konverterare"
    },
    {
      "type": "gap",
      "variant": "line"
    },
    {
      "type": "toolsCarousel",
      "title": "Utforska fler gratisverktyg"
    }
  ]
}
